sqla_client/__init__.py
sqla_client/client.py
sqla_client/date_ranges.py
sqla_client/examples/__init__.py
sqla_client/examples/clone_dashboard_and_queries.py
sqla_client/examples/query_export.py
sqla_client-0.0.1.dist-info/entry_points.txt
sqla_client-0.0.1.dist-info/LICENSE
sqla_client-0.0.1.dist-info/WHEEL
sqla_client-0.0.1.dist-info/METADATA
sqla_client-0.0.1.dist-info/RECORD
