Metadata-Version: 2.1
Name: sqla-client
Version: 0.0.1
Summary: SQL Analytics API client and tools to manage your instance.
License: BSD-2-Clause
Author: Databricks Engineering
Requires-Python: >=3.6,<4.0
Classifier: License :: OSI Approved :: BSD License
Classifier: Programming Language :: Python :: 3
Classifier: Programming Language :: Python :: 3.6
Classifier: Programming Language :: Python :: 3.7
Classifier: Programming Language :: Python :: 3.8
Classifier: Programming Language :: Python :: 3.9
Requires-Dist: click (>=7.0,<8.0)
Requires-Dist: requests (>=2.22.0,<3.0.0)
